{
  "name": "Business_Inventory/item-images/2026-01-22T00-58-14-635/1769043494635_image.jpg",
  "bucket": "ledger-nine4.appspot.com",
  "metageneration": 1,
  "generation": 1770332739118,
  "contentType": "image/jpeg",
  "storageClass": "STANDARD",
  "downloadTokens": [],
  "etag": "Fjw+3p5w5cCp/x9CtEqIMiiGgg0",
  "customMetadata": {
    "originalMediaId": "2106d80ee8f72e672e6860292ab5e39b578f943c21077f69de0b107a5ea8a298",
    "kind": "image"
  },
  "timeCreated": "2026-02-05T23:05:39.118Z",
  "updated": "2026-02-05T23:05:39.118Z",
  "size": 354850,
  "md5Hash": "KRr/Jpq0UMeeySxTGflZ7w==",
  "crc32c": "4113888423"
}
