{
  "name": "Hyer_s_Martinique_Rental/item-images/2026-01-12T21-07-17-281/1768252037281_image.jpg",
  "bucket": "demo-ledger.appspot.com",
  "metageneration": 1,
  "generation": 1770332742976,
  "contentType": "image/jpeg",
  "storageClass": "STANDARD",
  "downloadTokens": [],
  "etag": "4iNRuvwtdwMK5TOVb/W0M+nFm4g",
  "customMetadata": {
    "originalMediaId": "6bbbc8b4acfe080dc30497eaa7b53d1c6d8faef6006b5fa9175c3d0e466edfe4",
    "kind": "image"
  },
  "timeCreated": "2026-02-05T23:05:42.976Z",
  "updated": "2026-02-05T23:05:42.976Z",
  "size": 317239,
  "md5Hash": "HrOIDsbM5/dPQElIS7E74A==",
  "crc32c": "3153724416"
}