{
  "name": "Hyer_s_Martinique_Rental/item-images/2026-01-20T16-50-00-535/1768927800535_IMG_2710.jpeg",
  "bucket": "ledger-nine4.appspot.com",
  "metageneration": 1,
  "generation": 1770332738038,
  "contentType": "image/jpeg",
  "storageClass": "STANDARD",
  "downloadTokens": [],
  "etag": "yiP4KPWhT0yZ2UWsg2R2buZydn4",
  "customMetadata": {
    "originalMediaId": "0aa2a410d76d7af442432b411f8de64d6de3766046a44dc0716c311d5548445c",
    "kind": "image"
  },
  "timeCreated": "2026-02-05T23:05:38.038Z",
  "updated": "2026-02-05T23:05:38.038Z",
  "size": 229994,
  "md5Hash": "9p2xbhVBhWYAHZ6AisQBdQ==",
  "crc32c": "1842664413"
}
