{
  "name": "Bradshaws_Desert_Color_Rental/receipt-attachments/2026-01-11T23-31-35-580/1768174295580_image.jpg",
  "bucket": "ledger-nine4.appspot.com",
  "metageneration": 1,
  "generation": 1770332749455,
  "contentType": "image/jpeg",
  "storageClass": "STANDARD",
  "downloadTokens": [],
  "etag": "DObN8pZAdgrCBGsgUl1CpequBV0",
  "customMetadata": {
    "originalMediaId": "e9ca50cc382de2123f2b27cba6b83b6627a73e84f4f7e9a19082350c57814958",
    "kind": "image"
  },
  "timeCreated": "2026-02-05T23:05:49.455Z",
  "updated": "2026-02-05T23:05:49.455Z",
  "size": 2622968,
  "md5Hash": "0r/fkqYqWFP6vS2GlspYNg==",
  "crc32c": "1900793366"
}
