{
  "name": "Unknown_Project/item-images/2026-02-01T19-04-06-735/1769972646735_image.jpg",
  "bucket": "demo-ledger.appspot.com",
  "metageneration": 1,
  "generation": 1770332746117,
  "contentType": "image/jpeg",
  "storageClass": "STANDARD",
  "downloadTokens": [],
  "etag": "n5dJ8IJqAxYaiPye2Fr9oyC71H4",
  "customMetadata": {
    "originalMediaId": "a1ba17519f95282164bb0ad3ff05647d3e0e96bb466899d4e9df3ec53ea593db",
    "kind": "image"
  },
  "timeCreated": "2026-02-05T23:05:46.117Z",
  "updated": "2026-02-05T23:05:46.117Z",
  "size": 342668,
  "md5Hash": "eQFKDuomWuZ16LHl/1UVJQ==",
  "crc32c": "3869784950"
}