{
  "name": "Hyer_s_Martinique_Rental/item-images/2025-12-30T20-42-34-212/1767127354212_image.jpg",
  "bucket": "ledger-nine4.appspot.com",
  "metageneration": 1,
  "generation": 1770332742654,
  "contentType": "image/jpeg",
  "storageClass": "STANDARD",
  "downloadTokens": [],
  "etag": "xWCF7j+7M7NjXkwYDm2VxNl6mlc",
  "customMetadata": {
    "originalMediaId": "663afaf450fbe7b0dd680dda9d3b5d3b912c9269c7d136b9c8b5a6eb296f2c17",
    "kind": "image"
  },
  "timeCreated": "2026-02-05T23:05:42.654Z",
  "updated": "2026-02-05T23:05:42.654Z",
  "size": 370019,
  "md5Hash": "0wrhaDSc8de+s037zfTVUQ==",
  "crc32c": "1084013687"
}
