{
  "name": "Hyer_s_Martinique_Rental/item-images/2026-01-20T20-19-20-273/1768940360273_image.jpg",
  "bucket": "ledger-nine4.appspot.com",
  "metageneration": 1,
  "generation": 1770332737782,
  "contentType": "image/jpeg",
  "storageClass": "STANDARD",
  "downloadTokens": [],
  "etag": "7CROCqmdSqJWUOg/vSan53DQ2cw",
  "customMetadata": {
    "originalMediaId": "07dfc9af729afb3d592288a45c4e914121d2ebbea7c705e708f26952e53bac88",
    "kind": "image"
  },
  "timeCreated": "2026-02-05T23:05:37.782Z",
  "updated": "2026-02-05T23:05:37.782Z",
  "size": 578224,
  "md5Hash": "WRs33vpRIR0Uhv6/crzGAQ==",
  "crc32c": "3925002824"
}
