{
  "name": "Bradshaws_Desert_Color_Rental/item-images/2026-01-11T23-48-28-909/1768175308909_image.jpg",
  "bucket": "demo-ledger.appspot.com",
  "metageneration": 1,
  "generation": 1770332738557,
  "contentType": "image/jpeg",
  "storageClass": "STANDARD",
  "downloadTokens": [],
  "etag": "NNWDcqkB839/bSMalQJ72LX7LO4",
  "customMetadata": {
    "originalMediaId": "12a6c32b7f29618c726af6e6efa69cc17cfb4815687ec86e96ea1c0f37fab795",
    "kind": "image"
  },
  "timeCreated": "2026-02-05T23:05:38.557Z",
  "updated": "2026-02-05T23:05:38.557Z",
  "size": 452309,
  "md5Hash": "LNhn3OV42lH405weF93akA==",
  "crc32c": "1255098715"
}