{
  "name": "Bradshaws_Desert_Color_Rental/receipt-attachments/2026-01-11T21-58-40-232/1768168720232_image.jpg",
  "bucket": "ledger-nine4.appspot.com",
  "metageneration": 1,
  "generation": 1770332739593,
  "contentType": "image/jpeg",
  "storageClass": "STANDARD",
  "downloadTokens": [],
  "etag": "GKmHyT6+Nrgnr+dgmLubdg1K8+o",
  "customMetadata": {
    "originalMediaId": "265dac1e13d003d337787b465870532152ba8a18a020beb130496766bdfdf8c1",
    "kind": "image"
  },
  "timeCreated": "2026-02-05T23:05:39.593Z",
  "updated": "2026-02-05T23:05:39.593Z",
  "size": 3088635,
  "md5Hash": "skuWY7dYXZXtibu4C76rDQ==",
  "crc32c": "739284792"
}
